rich_LogConsole/__init__.py
rich_LogConsole-1.0.3.dist-info/LICENSE
rich_LogConsole-1.0.3.dist-info/METADATA
rich_LogConsole-1.0.3.dist-info/WHEEL
rich_LogConsole-1.0.3.dist-info/top_level.txt
rich_LogConsole-1.0.3.dist-info/RECORD
