Metadata-Version: 2.1
Name: rich-LogConsole
Version: 1.0.3
Summary: 一个实现了在一定高度自动滚动的 rich 日志组件，有两种刷新方式，建议配合Layout、Panel等组件使用。
Home-page: https://github.com/WankkoRee/rich-LogConsole
Author: Wankko Ree
Author-email: wkr@wkr.moe
License: GPLv3
Project-URL: Bug Tracker, https://github.com/WankkoRee/rich-LogConsole/issues
Platform: UNKNOWN
Classifier: Development Status :: 4 - Beta
Classifier: Programming Language :: Python :: 3 :: Only
Classifier: Programming Language :: Python :: 3.7
Classifier: Programming Language :: Python :: 3.8
Classifier: Programming Language :: Python :: 3.9
Classifier: License :: OSI Approved :: GNU General Public License v3 (GPLv3)
Classifier: Operating System :: OS Independent
Classifier: Natural Language :: Chinese (Simplified)
Classifier: Natural Language :: English
Requires-Python: >=3.7
License-File: LICENSE
Requires-Dist: rich (~=10.10.0)
